apiverve_phonevalidator/__init__.py
apiverve_phonevalidator/apiClient.py
apiverve_phonevalidator/exceptions.py
apiverve_phonevalidator/setup.py
apiverve_phonevalidator/tests/__init__.py
apiverve_phonevalidator/tests/test_api.py
apiverve_phonevalidator-1.1.2.dist-info/LICENSE
apiverve_phonevalidator-1.1.2.dist-info/METADATA
apiverve_phonevalidator-1.1.2.dist-info/WHEEL
apiverve_phonevalidator-1.1.2.dist-info/top_level.txt
apiverve_phonevalidator-1.1.2.dist-info/RECORD
